LICENSE
README.md
pyproject.toml
setup.cfg
setup.py
tests/__init__.py
tests/constants.py
tests/test_cli.py
tests/test_validate.py
tsvalid/__init__.py
tsvalid/__main__.py
tsvalid/checks.py
tsvalid/cli.py
tsvalid/constants.py
tsvalid/io.py
tsvalid/tsvalid.py
tsvalid/util.py
tsvalid.egg-info/PKG-INFO
tsvalid.egg-info/SOURCES.txt
tsvalid.egg-info/dependency_links.txt
tsvalid.egg-info/entry_points.txt
tsvalid.egg-info/not-zip-safe
tsvalid.egg-info/requires.txt
tsvalid.egg-info/top_level.txt