Metadata-Version: 2.1
Name: tsvalid
Version: 0.0.4
Summary: Validation of TSV files
Home-page: https://github.com/ontodev/tsvalid
Download-URL: https://github.com/ontodev/tsvalid/releases
Author: Nicolas Matentzoglu
Author-email: nicolas.matentzoglu@gmail.com
Maintainer: James Overton
Maintainer-email: james@overton.ca
License: MIT
Project-URL: Bug Tracker, https://github.com/ontodev/tsvalid/issues
Project-URL: Source Code, https://github.com/ontodev/tsvalid/
Project-URL: Documentation, https://ontodev.github.io/tsvalid
Keywords: TSV,Spreadsheet,Tables,Linter,Validation
Classifier: Development Status :: 3 - Alpha
Classifier: Environment :: Console
Classifier: Intended Audience :: Developers
Classifier: Intended Audience :: Science/Research
Classifier: License :: OSI Approved :: MIT License
Classifier: Operating System :: OS Independent
Classifier: Programming Language :: Python
Classifier: Programming Language :: Python :: 3.8
Classifier: Programming Language :: Python :: 3.7
Classifier: Programming Language :: Python :: 3 :: Only
Classifier: Topic :: Scientific/Engineering :: Bio-Informatics
Requires-Python: >=3.6
Provides-Extra: test
Provides-Extra: docs
License-File: LICENSE
